[
        {
            "id": "1",
            "name": "A & B"
        },
        {
            "id": "2",
            "name": "A & B Food Industries"
        },
        {
            "id": "3",
            "name": "A & G Travel And Tours"
        },
        {
            "id": "4",
            "name": "A & H Consulting"
        },
        {
            "id": "5",
            "name": "A & X Communications"
        },
        {
            "id": "6",
            "name": "A 2 Design"
        },
        {
            "id": "7",
            "name": "A C Nielsen Pakistan (Pvt.) Ltd"
        },
        {
            "id": "8",
            "name": "A Corporation"
        },
        {
            "id": "9",
            "name": "A F Ferguson & Company"
        },
        {
            "id": "10",
            "name": "A Faiq's Law Firm"
        },
        {
            "id": "11",
            "name": "A H Marketing"
        },
        {
            "id": "12",
            "name": "A Hardsoft Solution"
        },
        {
            "id": "13",
            "name": "A J Enterprises"
        },
        {
            "id": "14",
            "name": "A K Associates"
        },
        {
            "id": "15",
            "name": "A Kollective"
        },
        {
            "id": "16",
            "name": "A L House"
        },
        {
            "id": "17",
            "name": "A Q P H"
        },
        {
            "id": "18",
            "name": "A Regalia ( Pvt ) Ltd."
        },
        {
            "id": "19",
            "name": "A S Zerak (Pvt) Ltd"
        },
        {
            "id": "20",
            "name": "A Seven Group Tech"
        },
        {
            "id": "21",
            "name": "A T Markets"
        },
        {
            "id": "22",
            "name": "A TEL Pvt Limited"
        },
        {
            "id": "23",
            "name": "A to Zee Engineering Services"
        },
        {
            "id": "24",
            "name": "A Z Sense"
        },
        {
            "id": "25",
            "name": "A&A"
        },
        {
            "id": "26",
            "name": "A&A Associates"
        },
        {
            "id": "27",
            "name": "A&A Enterprises"
        },
        {
            "id": "28",
            "name": "A&C"
        },
        {
            "id": "29",
            "name": "A&I communication"
        },
        {
            "id": "30",
            "name": "A&I Engineering"
        },
        {
            "id": "31",
            "name": "A&J Deftek Consultants"
        },
        {
            "id": "32",
            "name": "A&M Enterprises"
        },
        {
            "id": "33",
            "name": "A&M Partners"
        },
        {
            "id": "34",
            "name": "A&S IT Solution"
        },
        {
            "id": "35",
            "name": "A&T Communication Co."
        },
        {
            "id": "36",
            "name": "A-1 Group of Companies"
        },
        {
            "id": "37",
            "name": "A-1 Handicraft"
        },
        {
            "id": "38",
            "name": "A-1 Websolutions"
        },
        {
            "id": "39",
            "name": "A-One Enterprises"
        },
        {
            "id": "40",
            "name": "A-Real Fast Technologies"
        },
        {
            "id": "41",
            "name": "A-Tech Design Interactive Studioz"
        },
        {
            "id": "42",
            "name": "A-Traders"
        },
        {
            "id": "43",
            "name": "A. H. Holdings Limited"
        },
        {
            "id": "44",
            "name": "A. Multilinks Pvt Limited"
        },
        {
            "id": "45",
            "name": "A. R. Ali & Co"
        },
        {
            "id": "46",
            "name": "A. Regalia (Pvt.) LTD"
        },
        {
            "id": "47",
            "name": "A.A Communication Pvt. Ltd"
        },
        {
            "id": "48",
            "name": "A.A Joyland Pvt Ltd."
        },
        {
            "id": "49",
            "name": "A.A. Consultants"
        },
        {
            "id": "50",
            "name": "A.A. Foods"
        },
        {
            "id": "51",
            "name": "A.A. International"
        },
        {
            "id": "52",
            "name": "A.A.B Inc"
        },
        {
            "id": "53",
            "name": "A.B. & Sons Packages"
        },
        {
            "id": "54",
            "name": "A.B.Estate"
        },
        {
            "id": "55",
            "name": "A.F Furguson & CO Lahore"
        },
        {
            "id": "56",
            "name": "A.F. Ferguson & Co"
        },
        {
            "id": "57",
            "name": "A.F. Ventures"
        },
        {
            "id": "58",
            "name": "A.F.Ferguson & Co"
        },
        {
            "id": "59",
            "name": "A.G.E Industries (Pvt) Ltd"
        },
        {
            "id": "60",
            "name": "A.G.E. Industries (Pvt) Ltd."
        },
        {
            "id": "61",
            "name": "A.H.Industries"
        },
        {
            "id": "62",
            "name": "A.H.Y Industries"
        },
        {
            "id": "63",
            "name": "A.I Textile"
        },
        {
            "id": "64",
            "name": "A.I TEXTILES"
        },
        {
            "id": "65",
            "name": "A.I. Training & Consultancy"
        },
        {
            "id": "66",
            "name": "A.I.M. Services, Inc."
        },
        {
            "id": "67",
            "name": "A.I.MIR LLC"
        },
        {
            "id": "68",
            "name": "A.J Enterprises"
        },
        {
            "id": "69",
            "name": "A.J.R Metal Fabricators Pvt. Ltd"
        },
        {
            "id": "70",
            "name": "A.k Enterprises"
        },
        {
            "id": "71",
            "name": "A.K.M Hospital"
        },
        {
            "id": "72",
            "name": "A.K.Taj International"
        },
        {
            "id": "73",
            "name": "A.M Distributors"
        },
        {
            "id": "74",
            "name": "A.M International"
        },
        {
            "id": "75",
            "name": "A.M Shipping & Logistics"
        },
        {
            "id": "76",
            "name": "A.M Solutions"
        },
        {
            "id": "77",
            "name": "A.M. Distributors"
        },
        {
            "id": "78",
            "name": "A.M.Laliwala & Co."
        },
        {
            "id": "79",
            "name": "A.N.Q Associates"
        },
        {
            "id": "80",
            "name": "A.N.Z. Advertising Media Corporation Pvt. Ltd."
        },
        {
            "id": "81",
            "name": "A.P Moller Singapore PTE Ltd"
        },
        {
            "id": "82",
            "name": "A.R. Traders"
        },
        {
            "id": "83",
            "name": "A.R.K & Co."
        },
        {
            "id": "84",
            "name": "A.S International Trading Co."
        },
        {
            "id": "85",
            "name": "A.S. & Company"
        },
        {
            "id": "86",
            "name": "A.S. Developers"
        },
        {
            "id": "87",
            "name": "A.S.I.A (American School of International Academics) Lahore"
        },
        {
            "id": "88",
            "name": "A.T international consultants"
        },
        {
            "id": "89",
            "name": "A.T.S Group of Companies"
        },
        {
            "id": "90",
            "name": "A1Call Center"
        },
        {
            "id": "91",
            "name": "A2Z College of Business & IT"
        },
        {
            "id": "92",
            "name": "A2Z Creatorz"
        },
        {
            "id": "93",
            "name": "a2z Edge PVT"
        },
        {
            "id": "94",
            "name": "A2Z Research Consultants"
        },
        {
            "id": "95",
            "name": "A2Z Tech Solutions"
        },
        {
            "id": "96",
            "name": "A3E Systems"
        },
        {
            "id": "97",
            "name": "A5 Group ( Pvt ) Ltd"
        },
        {
            "id": "98",
            "name": "A5tech"
        },
        {
            "id": "99",
            "name": "AA Commodities Pvt Ltd LHR"
        },
        {
            "id": "100",
            "name": "AA Consultant"
        },
        {
            "id": "101",
            "name": "AA Cotton Mills LTD"
        },
        {
            "id": "102",
            "name": "AA Exchange Co. Franchise"
        },
        {
            "id": "103",
            "name": "AA Exchange Company (Pvt) Ltd."
        },
        {
            "id": "104",
            "name": "AA GROUP"
        },
        {
            "id": "105",
            "name": "AA I & Associates LLC"
        },
        {
            "id": "106",
            "name": "AA Intelligent Systems"
        },
        {
            "id": "107",
            "name": "AA International"
        },
        {
            "id": "108",
            "name": "AA Joyland (Pvt) Ltd"
        },
        {
            "id": "109",
            "name": "AA Legal Group"
        },
        {
            "id": "110",
            "name": "AA Marketing"
        },
        {
            "id": "111",
            "name": "AA Media Productions"
        },
        {
            "id": "112",
            "name": "AA SEO"
        },
        {
            "id": "113",
            "name": "AA Spinning Mills Ltd"
        },
        {
            "id": "114",
            "name": "AA Spinning mills Pvt Ltd"
        },
        {
            "id": "115",
            "name": "AA Telecom"
        },
        {
            "id": "116",
            "name": "AA Tracker (Pvt) Ltd."
        },
        {
            "id": "117",
            "name": "AA'LA Solutions"
        },
        {
            "id": "118",
            "name": "AA-TECH"
        },
        {
            "id": "119",
            "name": "AAA"
        },
        {
            "id": "120",
            "name": "AAA BPO Services"
        },
        {
            "id": "121",
            "name": "AAA Emp Solutions"
        },
        {
            "id": "122",
            "name": "AAA Facility Management"
        },
        {
            "id": "123",
            "name": "AAA Info Soft"
        },
        {
            "id": "124",
            "name": "AAA Links"
        },
        {
            "id": "125",
            "name": "AAA Publications Pvt Ltd"
        },
        {
            "id": "126",
            "name": "AAA Technologies"
        },
        {
            "id": "127",
            "name": "AAAIII Group of Companies"
        },
        {
            "id": "128",
            "name": "AAAR Graphics"
        },
        {
            "id": "129",
            "name": "AAB(Pvt.) Ltd."
        },
        {
            "id": "130",
            "name": "Aabacus Synidcate (PVT) LTD"
        },
        {
            "id": "131",
            "name": "Aaban Nanotechnologies Pvt Ltd."
        },
        {
            "id": "132",
            "name": "AABCO fze"
        },
        {
            "id": "133",
            "name": "AABizSol"
        },
        {
            "id": "134",
            "name": "Aadil Teaching Hospital"
        },
        {
            "id": "135",
            "name": "AAGETWAY"
        },
        {
            "id": "136",
            "name": "Aaghaz Society"
        },
        {
            "id": "137",
            "name": "Aahung"
        },
        {
            "id": "138",
            "name": "AAJ Group Of Companies"
        },
        {
            "id": "139",
            "name": "Aaj Properties"
        },
        {
            "id": "140",
            "name": "AAJ Television"
        },
        {
            "id": "141",
            "name": "Aalams Groups"
        },
        {
            "id": "142",
            "name": "AAlimitedUK"
        },
        {
            "id": "143",
            "name": "aalogics"
        },
        {
            "id": "144",
            "name": "Aalpha Communication"
        },
        {
            "id": "145",
            "name": "Aamir Academy"
        },
        {
            "id": "146",
            "name": "Aamir Cargo Career"
        },
        {
            "id": "147",
            "name": "Aamtax Inc."
        },
        {
            "id": "148",
            "name": "AAN Associates"
        },
        {
            "id": "149",
            "name": "AAN Associates."
        },
        {
            "id": "150",
            "name": "AAN Technologies"
        },
        {
            "id": "151",
            "name": "Aansol (Pvt) Ltd."
        },
        {
            "id": "152",
            "name": "AAORP"
        },
        {
            "id": "153",
            "name": "AAR Global (Pvt.) Limited"
        },
        {
            "id": "154",
            "name": "Aaraib Tuition Academy"
        },
        {
            "id": "155",
            "name": "Aaramshop"
        },
        {
            "id": "156",
            "name": "Aaras Shipping Agencies"
        },
        {
            "id": "157",
            "name": "Aarknet"
        },
        {
            "id": "158",
            "name": "AarSol"
        },
        {
            "id": "159",
            "name": "Aasa International"
        },
        {
            "id": "160",
            "name": "Aasaas Foundation"
        },
        {
            "id": "161",
            "name": "Aashiyana Industries"
        },
        {
            "id": "162",
            "name": "Aaskar International"
        },
        {
            "id": "163",
            "name": "AASM"
        },
        {
            "id": "164",
            "name": "Aasma Textile"
        },
        {
            "id": "165",
            "name": "AASR"
        },
        {
            "id": "166",
            "name": "Aasra General Hospital"
        },
        {
            "id": "167",
            "name": "Aavansoft"
        },
        {
            "id": "168",
            "name": "AAWAZ"
        },
        {
            "id": "169",
            "name": "Aax"
        },
        {
            "id": "170",
            "name": "Aayan Services"
        },
        {
            "id": "171",
            "name": "Aayan Shayaan International"
        },
        {
            "id": "172",
            "name": "AAZ Communications"
        },
        {
            "id": "173",
            "name": "AB Communications"
        },
        {
            "id": "174",
            "name": "AB Consulting"
        },
        {
            "id": "175",
            "name": "AB Enterprises"
        },
        {
            "id": "176",
            "name": "AB Estates"
        },
        {
            "id": "177",
            "name": "AB Event Management"
        },
        {
            "id": "178",
            "name": "AB INC"
        },
        {
            "id": "179",
            "name": "AB Technologies"
        },
        {
            "id": "180",
            "name": "AB Textile"
        },
        {
            "id": "181",
            "name": "Aba Ali Habib Securities"
        },
        {
            "id": "182",
            "name": "ABA Ali Habib Securities (PVT) LTD."
        },
        {
            "id": "183",
            "name": "Abacus Consulting"
        },
        {
            "id": "184",
            "name": "Abacus Consulting"
        },
        {
            "id": "185",
            "name": "Abacus Consulting"
        },
        {
            "id": "186",
            "name": "Abacus Consulting - Islamabad"
        },
        {
            "id": "187",
            "name": "Abacus Transcription"
        },
        {
            "id": "188",
            "name": "AbacusConsulting(Abacus House)"
        },
        {
            "id": "189",
            "name": "Abacusoft"
        },
        {
            "id": "190",
            "name": "AbacusTec"
        },
        {
            "id": "191",
            "name": "AbacusTec (Pvt) Ltd."
        },
        {
            "id": "192",
            "name": "Abad Clinic"
        },
        {
            "id": "193",
            "name": "ABAMCO Limited"
        },
        {
            "id": "194",
            "name": "Aban 4 Design"
        },
        {
            "id": "195",
            "name": "Abaska Technologies"
        },
        {
            "id": "196",
            "name": "ABB Recruitment Firm"
        },
        {
            "id": "197",
            "name": "Abbas Technologies"
        },
        {
            "id": "198",
            "name": "Abbasi and Company (Pvt.) Ltd."
        },
        {
            "id": "199",
            "name": "Abbasi Securities (Pvt) Ltd."
        },
        {
            "id": "200",
            "name": "Abbasi Traders"
        },
        {
            "id": "201",
            "name": "Abbey Financial Services"
        },
        {
            "id": "202",
            "name": "Abbott International Ltd"
        },
        {
            "id": "203",
            "name": "Abbusys Ltd"
        },
        {
            "id": "204",
            "name": "ABC (Pvt) Ltd"
        },
        {
            "id": "205",
            "name": "ABC Academy of Business Computers"
        },
        {
            "id": "206",
            "name": "ABC Companies"
        },
        {
            "id": "207",
            "name": "ABC Consultants"
        },
        {
            "id": "208",
            "name": "ABC Consulting"
        },
        {
            "id": "209",
            "name": "ABC Corp"
        },
        {
            "id": "210",
            "name": "ABC International"
        },
        {
            "id": "211",
            "name": "ABC Neelam Ghar"
        },
        {
            "id": "212",
            "name": "ABC Travels"
        },
        {
            "id": "213",
            "name": "ABCD Learning Center"
        },
        {
            "id": "214",
            "name": "ABCHelpers"
        },
        {
            "id": "215",
            "name": "Abco Industries Limited"
        },
        {
            "id": "216",
            "name": "Abdohoo"
        },
        {
            "id": "217",
            "name": "Abdul Aziz Savul & Co."
        },
        {
            "id": "218",
            "name": "Abdul Hameed And Sons"
        },
        {
            "id": "219",
            "name": "Abdul Khalid & Co."
        },
        {
            "id": "220",
            "name": "Abdul Mohsen Al Sultan Est (Labomatic)"
        },
        {
            "id": "221",
            "name": "Abdul Waheed International"
        },
        {
            "id": "222",
            "name": "Abdulla Fouad Holding Co."
        },
        {
            "id": "223",
            "name": "Abdullah Brothers"
        },
        {
            "id": "224",
            "name": "Abdullah International Marketing Services"
        },
        {
            "id": "225",
            "name": "Abdullah Marketing"
        },
        {
            "id": "226",
            "name": "Abdullah Solutions"
        },
        {
            "id": "227",
            "name": "Abdullah Technology Solutions"
        },
        {
            "id": "228",
            "name": "Abdullah textile"
        },
        {
            "id": "229",
            "name": "Abdullah Tours"
        },
        {
            "id": "230",
            "name": "Abdullah Yunas Communication (PVT) Ltd."
        },
        {
            "id": "231",
            "name": "Abdur  Rehman Printers"
        },
        {
            "id": "232",
            "name": "Abe's Business"
        },
        {
            "id": "233",
            "name": "Abeeraz Collection"
        },
        {
            "id": "234",
            "name": "Abid Agency"
        },
        {
            "id": "235",
            "name": "Abid Associates"
        },
        {
            "id": "236",
            "name": "Abideen Publishing"
        },
        {
            "id": "237",
            "name": "ABK Enterprises"
        },
        {
            "id": "238",
            "name": "Ablazed Studios"
        },
        {
            "id": "239",
            "name": "Able People"
        },
        {
            "id": "240",
            "name": "ABM Data Systems (Pvt.) Ltd"
        },
        {
            "id": "241",
            "name": "ABM Data Systems (Pvt.) Ltd."
        },
        {
            "id": "242",
            "name": "ABM Info Tech (Private) Limited"
        },
        {
            "id": "243",
            "name": "ABM Info Tech (Private) Limited."
        },
        {
            "id": "244",
            "name": "ABM Info Tech (Pvt) Ltd"
        },
        {
            "id": "245",
            "name": "ABM Info Tech Pvt Ltd"
        },
        {
            "id": "246",
            "name": "ABN AMRO Bank"
        },
        {
            "id": "247",
            "name": "ABN AMRO BANK Pakistan"
        },
        {
            "id": "248",
            "name": "ABN Call Centre"
        },
        {
            "id": "249",
            "name": "ABN Enterprises-Karachi"
        },
        {
            "id": "250",
            "name": "ABN Overseas Education (Pvt) Ltd."
        },
        {
            "id": "251",
            "name": "ABN Soft"
        },
        {
            "id": "252",
            "name": "Abn Soft."
        },
        {
            "id": "253",
            "name": "AboutUs Pvt. Ltd."
        },
        {
            "id": "254",
            "name": "ABR Consultants"
        },
        {
            "id": "255",
            "name": "ABRAQ Institute of Management Sciences"
        },
        {
            "id": "256",
            "name": "Abrar Communications"
        },
        {
            "id": "257",
            "name": "Abrar Consultancy Services"
        },
        {
            "id": "258",
            "name": "Abrar Mobile Communications"
        },
        {
            "id": "259",
            "name": "ABRR.net"
        },
        {
            "id": "260",
            "name": "ABS"
        },
        {
            "id": "261",
            "name": "Absoindigo Pvt Ltd"
        },
        {
            "id": "262",
            "name": "AbsoLogix"
        },
        {
            "id": "263",
            "name": "Absolute Scribe, Inc"
        },
        {
            "id": "264",
            "name": "Absolute Solutions"
        },
        {
            "id": "265",
            "name": "Absolute Travels and Tourism"
        },
        {
            "id": "266",
            "name": "Absolutebyte"
        },
        {
            "id": "267",
            "name": "AbsoluteSource"
        },
        {
            "id": "268",
            "name": "Absotech Pvt Ltd"
        },
        {
            "id": "269",
            "name": "Abstract Solution"
        },
        {
            "id": "270",
            "name": "ABTACH"
        },
        {
            "id": "271",
            "name": "Abtact"
        },
        {
            "id": "272",
            "name": "Abtex International Ltd."
        },
        {
            "id": "273",
            "name": "Abu Huzaifa & Company"
        },
        {
            "id": "274",
            "name": "Abu Junaid Traders"
        },
        {
            "id": "275",
            "name": "Abu Soomar Industries"
        },
        {
            "id": "276",
            "name": "Abu Waqas"
        },
        {
            "id": "277",
            "name": "Abu-Ghazaleh Intellectual Property Services, Pvt. Ltd."
        },
        {
            "id": "278",
            "name": "AbuBakar Traders"
        },
        {
            "id": "279",
            "name": "Abudawood Pakistan"
        },
        {
            "id": "280",
            "name": "Abudawood Trading Company"
        },
        {
            "id": "281",
            "name": "Abul Rehman associate"
        },
        {
            "id": "282",
            "name": "Abuzar Enterprises Honda House"
        },
        {
            "id": "283",
            "name": "ABY and Company (Pvt.) Limited"
        },
        {
            "id": "284",
            "name": "Acacia (Pvt) Ltd"
        },
        {
            "id": "285",
            "name": "Academic Expert OnLine"
        },
        {
            "id": "286",
            "name": "Academic Freelance Group"
        },
        {
            "id": "287",
            "name": "Academic Writers"
        },
        {
            "id": "288",
            "name": "Academic Writing Company"
        },
        {
            "id": "289",
            "name": "Academic Writing Experts"
        },
        {
            "id": "290",
            "name": "Academics & Technical Training Institute"
        },
        {
            "id": "291",
            "name": "Academics Advisory Services Pakistan"
        },
        {
            "id": "292",
            "name": "Academy of Professional Accountants"
        },
        {
            "id": "293",
            "name": "ACBMS Pvt Limited"
        },
        {
            "id": "294",
            "name": "ACC10"
        },
        {
            "id": "295",
            "name": "ACCA"
        },
        {
            "id": "296",
            "name": "Accelera Technologies"
        },
        {
            "id": "297",
            "name": "Accenture"
        },
        {
            "id": "298",
            "name": "Accentys, INC"
        },
        {
            "id": "299",
            "name": "Access Communication Solution (Pvt) LTD"
        },
        {
            "id": "300",
            "name": "Access Communication Solutions"
        },
        {
            "id": "301",
            "name": "Access Consulting"
        },
        {
            "id": "302",
            "name": "Access Engineering Pvt. Ltd"
        },
        {
            "id": "303",
            "name": "Access Group"
        },
        {
            "id": "304",
            "name": "Access Group Pvt Ltd"
        },
        {
            "id": "305",
            "name": "Access Logistics Pvt Ltd"
        },
        {
            "id": "306",
            "name": "Access Marketing"
        },
        {
            "id": "307",
            "name": "Access pk"
        },
        {
            "id": "308",
            "name": "Access Retail"
        },
        {
            "id": "309",
            "name": "Access Retail Pvt.ltd."
        },
        {
            "id": "310",
            "name": "Access Security Services (Pvt) Ltd"
        },
        {
            "id": "311",
            "name": "Access Solution"
        },
        {
            "id": "312",
            "name": "Access Technologies"
        },
        {
            "id": "313",
            "name": "Access Telecom"
        },
        {
            "id": "314",
            "name": "Access World Services Pvt Ltd"
        },
        {
            "id": "315",
            "name": "Accessglobal(Pvt)Ltd"
        },
        {
            "id": "316",
            "name": "Accessories & Jewelry"
        },
        {
            "id": "317",
            "name": "AccessTek Pvt Ltd"
        },
        {
            "id": "318",
            "name": "Accesstek Transcriptions"
        },
        {
            "id": "319",
            "name": "Accotax Limited"
        },
        {
            "id": "320",
            "name": "Accountability Recruitment Ltd"
        },
        {
            "id": "321",
            "name": "Accountancy Outsourcing Services (Pvt.) Ltd."
        },
        {
            "id": "322",
            "name": "Accounting & Tax Associates"
        },
        {
            "id": "323",
            "name": "Accounts Management Association"
        },
        {
            "id": "324",
            "name": "Accu Traders (Pvt) Ltd"
        },
        {
            "id": "325",
            "name": "Accunity"
        },
        {
            "id": "326",
            "name": "Accurate Security Systems (Pvt) Ltd."
        },
        {
            "id": "327",
            "name": "Accurate Services Pakistan"
        },
        {
            "id": "328",
            "name": "Accuray Surgicals Limited"
        },
        {
            "id": "329",
            "name": "Accure Tech"
        },
        {
            "id": "330",
            "name": "ACE - Transportation Division"
        },
        {
            "id": "331",
            "name": "Ace Cargo Pvt Ltd"
        },
        {
            "id": "332",
            "name": "Ace Construction"
        },
        {
            "id": "333",
            "name": "ACE Consultants"
        },
        {
            "id": "334",
            "name": "ACE Consultants Islamabad"
        },
        {
            "id": "335",
            "name": "Ace Enterprises"
        },
        {
            "id": "336",
            "name": "Ace Indigio Industries (Pvt) Ltd"
        },
        {
            "id": "337",
            "name": "ACE Informatics"
        },
        {
            "id": "338",
            "name": "Ace Institute of Health Sciences"
        },
        {
            "id": "339",
            "name": "Ace Institute of Modern Sciences"
        },
        {
            "id": "340",
            "name": "Ace International"
        },
        {
            "id": "341",
            "name": "ACE Outsourcing Solutions"
        },
        {
            "id": "342",
            "name": "Ace Pvt Ltd"
        },
        {
            "id": "343",
            "name": "ACE School"
        },
        {
            "id": "344",
            "name": "ACE Tuition Center"
        },
        {
            "id": "345",
            "name": "Ace Writers Inc."
        },
        {
            "id": "346",
            "name": "Ace Writers Inc."
        },
        {
            "id": "347",
            "name": "Ace-Art Pvt Ltd"
        },
        {
            "id": "348",
            "name": "ACEACAN"
        },
        {
            "id": "349",
            "name": "Aceaider"
        },
        {
            "id": "350",
            "name": "ACES Pvt. Ltd"
        },
        {
            "id": "351",
            "name": "Aces Research Team"
        },
        {
            "id": "352",
            "name": "AceViral"
        },
        {
            "id": "353",
            "name": "ACF International"
        },
        {
            "id": "354",
            "name": "ACF International | Action Against Hunger"
        },
        {
            "id": "355",
            "name": "Achha Dairies"
        },
        {
            "id": "356",
            "name": "Acid Survivors Foundation Pakistan"
        },
        {
            "id": "357",
            "name": "ACM Gold"
        },
        {
            "id": "358",
            "name": "ACM Gold (pvt) LTD"
        },
        {
            "id": "359",
            "name": "ACME Engineering & Services"
        },
        {
            "id": "360",
            "name": "Acme Financial Services"
        },
        {
            "id": "361",
            "name": "Acme Technologies"
        },
        {
            "id": "362",
            "name": "Acme Tel"
        },
        {
            "id": "363",
            "name": "AcmeLogic Systems"
        },
        {
            "id": "364",
            "name": "AcmeLogic Systems Pvt .Ltd"
        },
        {
            "id": "365",
            "name": "AcmeLogic Systems Pvt. Ltd."
        },
        {
            "id": "366",
            "name": "ACML"
        },
        {
            "id": "367",
            "name": "Acom Distributors"
        },
        {
            "id": "368",
            "name": "AConsulting Pvt Ltd"
        },
        {
            "id": "369",
            "name": "Acro Textile Mills Ltd"
        },
        {
            "id": "370",
            "name": "Acro Textile Mills Ltd."
        },
        {
            "id": "371",
            "name": "Acrobat Systems"
        },
        {
            "id": "372",
            "name": "Acrologix (Pvt) Limited"
        },
        {
            "id": "373",
            "name": "Acropetal Education System"
        },
        {
            "id": "374",
            "name": "Acrux Technologies"
        },
        {
            "id": "375",
            "name": "ACS Courier Company"
        },
        {
            "id": "376",
            "name": "ACS Textiles (Bangladesh) Ltd."
        },
        {
            "id": "377",
            "name": "ACTED Pakistan"
        },
        {
            "id": "378",
            "name": "Action Aid Pakistan"
        },
        {
            "id": "379",
            "name": "Activ8"
        },
        {
            "id": "380",
            "name": "Activa Financial Limited"
        },
        {
            "id": "381",
            "name": "Activation Sources"
        },
        {
            "id": "382",
            "name": "Active Business Solutions"
        },
        {
            "id": "383",
            "name": "Active Capital IT"
        },
        {
            "id": "384",
            "name": "Active Foods"
        },
        {
            "id": "385",
            "name": "Active Passive"
        },
        {
            "id": "386",
            "name": "Activekey Solutions Pvt."
        },
        {
            "id": "387",
            "name": "Activemedia"
        },
        {
            "id": "388",
            "name": "Activepace Ltd."
        },
        {
            "id": "389",
            "name": "Actsol (SMC Pvt) Ltd."
        },
        {
            "id": "390",
            "name": "Actual NIC"
        },
        {
            "id": "391",
            "name": "Actual Quality Services, Inc."
        },
        {
            "id": "392",
            "name": "Acube Technologies"
        },
        {
            "id": "393",
            "name": "Acumen Career Trainers"
        },
        {
            "id": "394",
            "name": "Acumen Fund"
        },
        {
            "id": "395",
            "name": "Acumen Prescience"
        },
        {
            "id": "396",
            "name": "Acumen Technologies"
        },
        {
            "id": "397",
            "name": "Acute Business College"
        },
        {
            "id": "398",
            "name": "Acute Graphics"
        },
        {
            "id": "399",
            "name": "Acute Group of Colleges"
        },
        {
            "id": "400",
            "name": "Acutech PtyLtd"
        },
        {
            "id": "401",
            "name": "Ad  Fort  Media"
        },
        {
            "id": "402",
            "name": "AD h.r.support"
        },
        {
            "id": "403",
            "name": "AD Logistics"
        },
        {
            "id": "404",
            "name": "Ad Makers"
        },
        {
            "id": "405",
            "name": "Ad-Point Advertising"
        },
        {
            "id": "406",
            "name": "Adabistan-e-Soophia Higher Secondary School"
        },
        {
            "id": "407",
            "name": "Adage Advertising (Pvt) Ltd."
        },
        {
            "id": "408",
            "name": "Adam Advertise"
        },
        {
            "id": "409",
            "name": "Adam Smith International"
        },
        {
            "id": "410",
            "name": "Adam Soft International"
        },
        {
            "id": "411",
            "name": "Adam Technologies"
        },
        {
            "id": "412",
            "name": "ADAM'S AID CORPORATION"
        },
        {
            "id": "413",
            "name": "Adamjee Computers"
        },
        {
            "id": "414",
            "name": "Adamjee Diesel Engineering Pakistan (Pvt.) Ltd."
        },
        {
            "id": "415",
            "name": "Adamjee Engineering (Pvt) Ltd."
        },
        {
            "id": "416",
            "name": "Adamjee Insurance Co. Ltd"
        },
        {
            "id": "417",
            "name": "Adamjee Insurance Company Limited"
        },
        {
            "id": "418",
            "name": "Adamjee Life Assurance Co. Ltd"
        },
        {
            "id": "419",
            "name": "Adamjee School"
        },
        {
            "id": "420",
            "name": "Adamjee School System"
        },
        {
            "id": "421",
            "name": "Adamjeelife Assurance Co. Ltd"
        },
        {
            "id": "422",
            "name": "Adams Fire Tech (pvt) Ltd"
        },
        {
            "id": "423",
            "name": "ADBellz"
        },
        {
            "id": "424",
            "name": "AdChrome Solutions"
        },
        {
            "id": "425",
            "name": "ADCITY"
        },
        {
            "id": "426",
            "name": "Adcok Pharmaceuticals(Pvt.)LTD"
        },
        {
            "id": "427",
            "name": "Adcore Productions"
        },
        {
            "id": "428",
            "name": "ADD Click"
        },
        {
            "id": "429",
            "name": "Adda Co"
        },
        {
            "id": "430",
            "name": "Addiction"
        },
        {
            "id": "431",
            "name": "Addictive Mobility"
        },
        {
            "id": "432",
            "name": "AddictiveTips"
        },
        {
            "id": "433",
            "name": "Addixtion Trading Company"
        },
        {
            "id": "434",
            "name": "Addo Coorporations"
        },
        {
            "id": "435",
            "name": "Addopt"
        },
        {
            "id": "436",
            "name": "Addvantum Innovative Technologies"
        },
        {
            "id": "437",
            "name": "Adeel Engineering Works"
        },
        {
            "id": "438",
            "name": "Adeel Khas Brothers"
        },
        {
            "id": "439",
            "name": "Adeel Magazine"
        },
        {
            "id": "440",
            "name": "Aden Technologies"
        },
        {
            "id": "441",
            "name": "Adept Writers"
        },
        {
            "id": "442",
            "name": "Adeptechs Pvt. Limited"
        },
        {
            "id": "443",
            "name": "AdeptSoft (Pvt) Ltd."
        },
        {
            "id": "444",
            "name": "Adex Interactive"
        },
        {
            "id": "445",
            "name": "ADG LDI (Pvt) Limited"
        },
        {
            "id": "446",
            "name": "Adgroup (Pvt) Ltd"
        },
        {
            "id": "447",
            "name": "Adhoc Technologies"
        },
        {
            "id": "448",
            "name": "Adidas Sourcing Limited"
        },
        {
            "id": "449",
            "name": "ADinfinity"
        },
        {
            "id": "450",
            "name": "Adiz Interactive"
        },
        {
            "id": "451",
            "name": "Adlinkers"
        },
        {
            "id": "452",
            "name": "ADM Denim"
        },
        {
            "id": "453",
            "name": "Admark"
        },
        {
            "id": "454",
            "name": "Admark Consultants"
        },
        {
            "id": "455",
            "name": "AdMark Solutions"
        },
        {
            "id": "456",
            "name": "ADMaster"
        },
        {
            "id": "457",
            "name": "AdMaxim (Pvt.) Limited."
        },
        {
            "id": "458",
            "name": "admen printers"
        },
        {
            "id": "459",
            "name": "Admill"
        },
        {
            "id": "460",
            "name": "Admission Advisors"
        },
        {
            "id": "461",
            "name": "Admission Advisors Pvt. Ltd"
        },
        {
            "id": "462",
            "name": "Admission Advisory"
        },
        {
            "id": "463",
            "name": "Adn Freelancer"
        },
        {
            "id": "464",
            "name": "Adnan Ad"
        },
        {
            "id": "465",
            "name": "Adnan Asdar & Associates"
        },
        {
            "id": "466",
            "name": "Adnan Corporation"
        },
        {
            "id": "467",
            "name": "Adnan Mudassar Chartered Accountants"
        },
        {
            "id": "468",
            "name": "adnanconstruction"
        },
        {
            "id": "469",
            "name": "Adnare Pvt. Ltd."
        },
        {
            "id": "470",
            "name": "Adnom Technology"
        },
        {
            "id": "471",
            "name": "Adonis Media"
        },
        {
            "id": "472",
            "name": "Adorasoft"
        },
        {
            "id": "473",
            "name": "Adorn Work"
        },
        {
            "id": "474",
            "name": "ADP"
        },
        {
            "id": "475",
            "name": "Adpro Link Advertising & Pvt Production"
        },
        {
            "id": "476",
            "name": "Adreach Advertising"
        },
        {
            "id": "477",
            "name": "AdReTek Business Solutions"
        },
        {
            "id": "478",
            "name": "Adroit"
        },
        {
            "id": "479",
            "name": "Adroit Pvt. Ltd"
        },
        {
            "id": "480",
            "name": "AdroitMB"
        },
        {
            "id": "481",
            "name": "Adsells"
        },
        {
            "id": "482",
            "name": "Adsells Advertising (Pvt.) Ltd."
        },
        {
            "id": "483",
            "name": "Adservice"
        },
        {
            "id": "484",
            "name": "ADSII"
        },
        {
            "id": "485",
            "name": "Adsim International"
        },
        {
            "id": "486",
            "name": "Adspress Media Pvt. Ltd"
        },
        {
            "id": "487",
            "name": "Adstyle"
        },
        {
            "id": "488",
            "name": "AdsZone"
        },
        {
            "id": "489",
            "name": "Adult Basic Education Society - Teacher Empowerment Centre (ABES-TEC)"
        },
        {
            "id": "490",
            "name": "Advance Business Centre"
        },
        {
            "id": "491",
            "name": "Advance Business Components"
        },
        {
            "id": "492",
            "name": "Advance Business Computing Technology"
        },
        {
            "id": "493",
            "name": "Advance Business Systems"
        },
        {
            "id": "494",
            "name": "Advance Communications"
        },
        {
            "id": "495",
            "name": "Advance Computer Learning Center"
        },
        {
            "id": "496",
            "name": "Advance Computers Systems"
        },
        {
            "id": "497",
            "name": "Advance Education Systems(Pvt) LTD."
        },
        {
            "id": "498",
            "name": "Advance Health Cure"
        },
        {
            "id": "499",
            "name": "Advance I-Tech Solutions"
        },
        {
            "id": "500",
            "name": "Advance International Chemicals Pvt Ltd"
        }
]